oflibnumpy/__init__.py
oflibnumpy/flow_class.py
oflibnumpy/flow_operations.py
oflibnumpy/utils.py
oflibnumpy-1.1.1.dist-info/LICENSE.txt
oflibnumpy-1.1.1.dist-info/METADATA
oflibnumpy-1.1.1.dist-info/WHEEL
oflibnumpy-1.1.1.dist-info/top_level.txt
oflibnumpy-1.1.1.dist-info/RECORD
