Metadata-Version: 2.1
Name: oflibnumpy
Version: 1.1.1
Summary: Optical flow library using a custom flow class based on NumPy arrays
Home-page: https://github.com/RViMLab/oflibnumpy
Author: Claudio S. Ravasio
Author-email: claudio.s.ravasio@gmail.com
License: MIT
Project-URL: Documentation, https://oflibnumpy.rtfd.io
Project-URL: Source, https://github.com/RViMLab/oflibnumpy
Project-URL: Tracker, https://github.com/RViMLab/oflibnumpy/issues
Keywords: optical flow,flow,flow field,flow composition,flow combination,flow visualisation
Platform: UNKNOWN
Classifier: Development Status :: 5 - Production/Stable
Classifier: License :: OSI Approved :: MIT License
Classifier: Programming Language :: Python :: 3
Requires-Python: >=3.7
License-File: LICENSE.txt
Requires-Dist: numpy
Requires-Dist: opencv-python
Requires-Dist: scipy
